locusts/__init__.py
locusts/data_transfer_protocol.sh
locusts/environment.py
locusts/inner_template_manager.txt
locusts/manager.py
locusts/outer_template_manager.txt
locusts/support.py
locusts/swarm.py
locusts-0.0.88.dist-info/licenses/LICENSE
locusts-0.0.88.dist-info/METADATA
locusts-0.0.88.dist-info/WHEEL
locusts-0.0.88.dist-info/top_level.txt
locusts-0.0.88.dist-info/RECORD
